README.rst
pypi_rst_ref.py
setup.py
pypi_rst_ref.egg-info/PKG-INFO
pypi_rst_ref.egg-info/SOURCES.txt
pypi_rst_ref.egg-info/dependency_links.txt
pypi_rst_ref.egg-info/top_level.txt