Metadata-Version: 1.0
Name: pypi-rst-ref
Version: 0.0.4
Summary: A reference for how reStructuredText blocks are rendered by Github and PyPI.
Home-page: https://github.com/moreati/pypi-rst-ref
Author: Alex Willmer
Author-email: alex@moreati.org.uk
License: Apache 2.0
Platform: UNKNOWN
